{
  "dialogs": [],
  "scrollY": 0,
  "text": "‹\n选择现有食材\n清空\nBUILD YOUR PLATE\n冰箱里有什么？\n\n挑选手边食材，我们为你组合更轻盈的一餐。\n\n⌕\n肉类海鲜\n蛋奶豆制品\n蔬菜菌菇\n主食薯类\n水果坚果\n3\n已选食材\n\n鸡胸肉、鸡蛋、番茄\n\n肉类海鲜\n\n高蛋白核心\n\n8 种\n鸡胸肉\n✓\n虾仁\n+\n牛肉\n+\n三文鱼\n+\n鸡腿肉\n+\n鳕鱼\n+\n金枪鱼\n+\n瘦猪肉\n+\n蛋奶豆制品\n\n日常补充蛋白\n\n8 种\n鸡蛋\n✓\n豆腐\n+\n无糖酸奶\n+\n牛奶\n+\n毛豆\n+\n鹰嘴豆\n+\n黑豆\n+\n低脂奶酪\n+\n蔬菜菌菇\n\n纤维与微量营养\n\n10 种\n黄瓜\n+\n西兰花\n+\n番茄\n✓\n菠菜\n+\n生菜\n+\n彩椒\n+\n芦笋\n+\n蘑菇\n+\n西葫芦\n+\n紫甘蓝\n+\n主食薯类\n\n稳定能量来源\n\n8 种\n糙米\n+\n燕麦\n+\n红薯\n+\n玉米\n+\n全麦面包\n+\n意面\n+\n藜麦\n+\n土豆\n+\n水果坚果\n\n轻食搭配与加餐\n\n8 种\n牛油果\n+\n蓝莓\n+\n香蕉\n+\n苹果\n+\n橙子\n+\n草莓\n+\n猕猴桃\n+\n混合坚果\n+\n根据 3 种食材找菜谱 →",
  "title": "轻食谱",
  "url": "https://light-flow-fit.netlify.app/"
}